datascribe_api/__init__.py
datascribe_api/__main__.py
datascribe_api/cli.py
datascribe_api/client.py
datascribe_api/client.pyi
datascribe_api/filter.py
datascribe_api/models.py
datascribe_api/py.typed
datascribe_api/routes.py
datascribe_api/utils.py
datascribe_api-1.0.2.dist-info/licenses/LICENSE
datascribe_api-1.0.2.dist-info/WHEEL
datascribe_api-1.0.2.dist-info/entry_points.txt
datascribe_api-1.0.2.dist-info/METADATA
datascribe_api-1.0.2.dist-info/RECORD
