Metadata-Version: 2.4
Name: datascribe-api
Version: 1.0.2
Summary: A Python client for the DataScribe API
Author: Doguhan Sariturk
Author-email: Doguhan Sariturk <dogu.sariturk@gmail.com>
License-Expression: GPL-3.0-only
License-File: LICENSE
Classifier: Development Status :: 5 - Production/Stable
Classifier: Intended Audience :: Developers
Classifier: Intended Audience :: Science/Research
Classifier: License :: OSI Approved :: GNU General Public License v3 (GPLv3)
Classifier: Operating System :: OS Independent
Classifier: Programming Language :: Python :: 3
Classifier: Topic :: Scientific/Engineering
Classifier: Topic :: Utilities
Classifier: Typing :: Typed
Requires-Dist: backoff>=2.2.1
Requires-Dist: pandas>=2.3.3
Requires-Dist: pydantic>=2.11.7
Requires-Dist: requests>=2.32.4
Requires-Dist: rich>=14.0.0
Requires-Dist: typer>=0.16.0
Requires-Dist: mkdocs>=1.6.1 ; extra == 'docs'
Requires-Dist: mkdocs-material>=9.6.21 ; extra == 'docs'
Requires-Dist: mkdocstrings-python>=1.18.2 ; extra == 'docs'
Requires-Python: >=3.11
Project-URL: Issues, https://github.com/DataScribe-Cloud/datascribe_api/issues
Project-URL: Repository, https://github.com/DataScribe-Cloud/datascribe_api
Provides-Extra: docs
